LICENSE
MANIFEST.in
README.rst
setup.py
Snake.egg-info/PKG-INFO
Snake.egg-info/SOURCES.txt
Snake.egg-info/dependency_links.txt
Snake.egg-info/entry_points.txt
Snake.egg-info/top_level.txt
snake/__init__.py
snake/api.py
snake/main.py
snake/state.py
snake/tasks.py
snake/utils.py