Metadata-Version: 1.0
Name: Snake
Version: 0.1.0
Summary: Snake is yet another Make-like tool inspired by Rake.
Home-page: http://github.com/yumike/snake
Author: Mike Yumatov
Author-email: mike@yumatov.org
License: UNKNOWN
Platform: UNKNOWN
